[
    {
        "children": [
            {
                "children": [
                    {
                        "children": [
                            {
                                "text": "Nuxt"
                            }
                        ],
                        "text": "Vue"
                    },
                    {
                        "children": [
                            {
                                "text": "Next"
                            }
                        ],
                        "text": "React"
                    },
                    {
                        "text": "Angular"
                    }
                ],
                "text": "Frontend"
            },
            {
                "text": "Backend"
            }
        ],
        "text": "Projects"
    },
    {
        "children": [
            {
                "children": [
                    {
                        "text": "The Godfather"
                    },
                    {
                        "text": "La Dolce Vita"
                    },
                    {
                        "text": "In the Mood for Love"
                    }
                ],
                "text": "Movie"
            },
            {
                "text": "AD"
            },
            {
                "text": "Shorts"
            }
        ],
        "text": "Videos"
    },
    {
        "children": [
            {
                "text": "Animals"
            },
            {
                "text": "Buildings"
            },
            {
                "text": "Sky"
            },
            {
                "text": "Sea"
            }
        ],
        "text": "Photos"
    },
    {
        "children": [
            {
                "text": "My Happy Melodies."
            },
            {
                "text": "Hello Summer."
            },
            {
                "text": "An Overture To Happiness."
            },
            {
                "text": "Sunny Days."
            },
            {
                "text": "Every One Need Adventure."
            },
            {
                "text": "Happy, Chill Radio."
            },
            {
                "text": "I Found My Way."
            },
            {
                "text": "Early, Early Morning."
            }
        ],
        "text": "Music"
    },
    {
        "children": [
            {
                "text": "swimming"
            },
            {
                "text": "cycling"
            },
            {
                "text": "tennis"
            },
            {
                "text": "boxing"
            }
        ],
        "text": "Games"
    },
    {
        "text": "Download"
    }
]
